claudesavvy/__init__.py
claudesavvy/__main__.py
claudesavvy/cli.py
claudesavvy/analyzers/__init__.py
claudesavvy/analyzers/configuration.py
claudesavvy/analyzers/features.py
claudesavvy/analyzers/integrations.py
claudesavvy/analyzers/project_analyzer.py
claudesavvy/analyzers/tokens.py
claudesavvy/analyzers/usage.py
claudesavvy/models/__init__.py
claudesavvy/parsers/__init__.py
claudesavvy/parsers/configuration_scanner.py
claudesavvy/parsers/debug.py
claudesavvy/parsers/files.py
claudesavvy/parsers/history.py
claudesavvy/parsers/sessions.py
claudesavvy/parsers/skills.py
claudesavvy/parsers/tools.py
claudesavvy/utils/__init__.py
claudesavvy/utils/paths.py
claudesavvy/utils/pricing.py
claudesavvy/utils/time_filter.py
claudesavvy/web/__init__.py
claudesavvy/web/app.py
claudesavvy/web/routes/__init__.py
claudesavvy/web/routes/api.py
claudesavvy/web/routes/charts.py
claudesavvy/web/routes/dashboard.py
claudesavvy/web/services/__init__.py
claudesavvy/web/services/chart_service.py
claudesavvy/web/services/dashboard_service.py
claudesavvy/web/static/css/.gitkeep
claudesavvy/web/static/js/.gitkeep
claudesavvy/web/templates/__init__.py
claudesavvy/web/templates/base.html
claudesavvy/web/templates/components/card.html
claudesavvy/web/templates/components/table.html
claudesavvy/web/templates/layouts/app.html
claudesavvy/web/templates/pages/__init__.py
claudesavvy/web/templates/pages/configuration.html
claudesavvy/web/templates/pages/dashboard.html
claudesavvy/web/templates/pages/error.html
claudesavvy/web/templates/pages/features.html
claudesavvy/web/templates/pages/files.html
claudesavvy/web/templates/pages/integrations.html
claudesavvy/web/templates/pages/projects.html
claudesavvy/web/templates/pages/settings.html
claudesavvy/web/templates/pages/tokens.html
claudesavvy/web/templates/partials/__init__.py
claudesavvy/web/templates/partials/cost_trend_charts.html
claudesavvy/web/templates/partials/dashboard_charts.html
claudesavvy/web/templates/partials/dashboard_content.html
claudesavvy-2.2.1.dist-info/licenses/LICENSE
claudesavvy-2.2.1.dist-info/METADATA
claudesavvy-2.2.1.dist-info/WHEEL
claudesavvy-2.2.1.dist-info/entry_points.txt
claudesavvy-2.2.1.dist-info/top_level.txt
claudesavvy-2.2.1.dist-info/RECORD
